{"matchId":"0ef83054-bf85-443c-ac10-342a0bdd5371","mapId":"GrandRift","date":"February_10","players":[{"userId":"94d042cb-a0f2-45f3-bdca-42fab73cfef5","isBot":false,"events":[{"x":162.16,"z":152.94,"y":29.66,"ts":1770748951,"ev":"Position"},{"x":182.54,"z":168.87,"y":31.21,"ts":1770748971,"ev":"Position"},{"x":183.06,"z":169.5,"y":31.19,"ts":1770748974,"ev":"Loot"},{"x":183.06,"z":169.5,"y":31.19,"ts":1770748974,"ev":"Loot"},{"x":174.89,"z":162.56,"y":31.29,"ts":1770748976,"ev":"Position"},{"x":153.7,"z":139.69,"y":30.76,"ts":1770748981,"ev":"Position"},{"x":138.98,"z":125.01,"y":33.98,"ts":1770748986,"ev":"Position"},{"x":138.63,"z":120.83,"y":33.98,"ts":1770748989,"ev":"Loot"},{"x":131.89,"z":115.6,"y":33.98,"ts":1770748991,"ev":"Position"},{"x":131.89,"z":115.6,"y":33.98,"ts":1770748994,"ev":"Loot"},{"x":131.89,"z":115.6,"y":33.98,"ts":1770748995,"ev":"Loot"},{"x":127.62,"z":108.19,"y":33.59,"ts":1770748996,"ev":"Position"},{"x":112.54,"z":104.43,"y":37.96,"ts":1770749001,"ev":"Position"},{"x":102.8,"z":125.19,"y":34.26,"ts":1770749006,"ev":"Position"},{"x":102.8,"z":125.19,"y":34.26,"ts":1770749007,"ev":"Loot"},{"x":86.81,"z":141.97,"y":32.53,"ts":1770749011,"ev":"Position"},{"x":76.62,"z":152.95,"y":31.91,"ts":1770749016,"ev":"Position"},{"x":76.74,"z":152.74,"y":31.94,"ts":1770749017,"ev":"Loot"},{"x":68.35,"z":142.07,"y":32.16,"ts":1770749021,"ev":"Position"},{"x":61.51,"z":120.57,"y":34.21,"ts":1770749026,"ev":"Position"},{"x":53.3,"z":98.46,"y":34.77,"ts":1770749032,"ev":"Position"},{"x":28.45,"z":89.3,"y":34.22,"ts":1770749037,"ev":"Position"},{"x":27.05,"z":92.61,"y":34.24,"ts":1770749042,"ev":"Position"},{"x":34.88,"z":79.85,"y":33.24,"ts":1770749047,"ev":"Position"},{"x":42.91,"z":63.99,"y":32.07,"ts":1770749052,"ev":"Position"},{"x":41.77,"z":57.33,"y":30.98,"ts":1770749057,"ev":"Position"},{"x":43.71,"z":52.27,"y":31.53,"ts":1770749067,"ev":"Position"},{"x":34.77,"z":57.48,"y":28.99,"ts":1770749082,"ev":"Position"},{"x":30.36,"z":82.31,"y":33.83,"ts":1770749087,"ev":"Position"},{"x":11.29,"z":89.91,"y":34.76,"ts":1770749092,"ev":"Position"},{"x":21.5,"z":86.98,"y":34.51,"ts":1770749097,"ev":"Position"},{"x":35.88,"z":71.67,"y":31.74,"ts":1770749102,"ev":"Position"},{"x":14.24,"z":59.64,"y":23.86,"ts":1770749107,"ev":"Position"},{"x":-0.38,"z":50.81,"y":16.34,"ts":1770749112,"ev":"Position"},{"x":-0.38,"z":50.81,"y":16.34,"ts":1770749112,"ev":"Loot"},{"x":-0.38,"z":50.81,"y":16.34,"ts":1770749113,"ev":"Loot"},{"x":-0.38,"z":50.81,"y":16.34,"ts":1770749114,"ev":"Loot"},{"x":-0.38,"z":50.81,"y":16.34,"ts":1770749114,"ev":"Loot"},{"x":0.06,"z":50.81,"y":16.36,"ts":1770749115,"ev":"Loot"},{"x":0.17,"z":50.81,"y":16.37,"ts":1770749116,"ev":"Loot"},{"x":0.17,"z":50.81,"y":16.37,"ts":1770749116,"ev":"Loot"},{"x":6.29,"z":55.89,"y":19.25,"ts":1770749122,"ev":"Position"},{"x":-2.46,"z":53.26,"y":16.53,"ts":1770749126,"ev":"BotKill"},{"x":-1.72,"z":52.35,"y":16.45,"ts":1770749127,"ev":"Position"},{"x":-6.76,"z":41.9,"y":14.92,"ts":1770749131,"ev":"Loot"},{"x":-6.52,"z":41.92,"y":14.93,"ts":1770749131,"ev":"Loot"},{"x":-6.15,"z":39.28,"y":14.28,"ts":1770749132,"ev":"Position"},{"x":-6.15,"z":35.65,"y":13.73,"ts":1770749135,"ev":"Loot"},{"x":-4.28,"z":29.63,"y":12.62,"ts":1770749137,"ev":"Position"},{"x":-3.13,"z":26.38,"y":12.2,"ts":1770749141,"ev":"Loot"},{"x":0.89,"z":33.8,"y":13.48,"ts":1770749147,"ev":"Position"},{"x":4.62,"z":41.48,"y":15.94,"ts":1770749152,"ev":"Position"},{"x":12.22,"z":18.32,"y":22.06,"ts":1770749157,"ev":"Position"},{"x":31.39,"z":-0.94,"y":25.03,"ts":1770749162,"ev":"Position"},{"x":54.44,"z":-19.68,"y":26.75,"ts":1770749167,"ev":"Position"},{"x":74.15,"z":-30.57,"y":24.52,"ts":1770749172,"ev":"Position"},{"x":97.15,"z":-38.72,"y":27.31,"ts":1770749177,"ev":"Position"},{"x":127.18,"z":-44.13,"y":25,"ts":1770749182,"ev":"Position"},{"x":156.9,"z":-37.12,"y":21.03,"ts":1770749187,"ev":"Position"},{"x":176.45,"z":-20.28,"y":21.18,"ts":1770749192,"ev":"Position"},{"x":176.41,"z":-19.38,"y":21.18,"ts":1770749195,"ev":"Loot"},{"x":185.92,"z":-21.42,"y":21.18,"ts":1770749197,"ev":"Position"},{"x":185.92,"z":-21.42,"y":21.18,"ts":1770749199,"ev":"Loot"},{"x":186.55,"z":-32.24,"y":21.18,"ts":1770749228,"ev":"Position"},{"x":178.81,"z":-41.47,"y":21.1,"ts":1770749233,"ev":"Position"},{"x":178.94,"z":-48.71,"y":21.02,"ts":1770749243,"ev":"Position"},{"x":171.29,"z":-48.07,"y":21.02,"ts":1770749248,"ev":"Position"},{"x":172.15,"z":-44.76,"y":21.02,"ts":1770749283,"ev":"Position"},{"x":183.04,"z":-44.67,"y":21.02,"ts":1770749288,"ev":"Position"},{"x":177.07,"z":-35.53,"y":21.02,"ts":1770749293,"ev":"Position"},{"x":180.29,"z":-40.35,"y":21.02,"ts":1770749303,"ev":"Position"},{"x":179.77,"z":-41.45,"y":21.07,"ts":1770749305,"ev":"Loot"},{"x":179.77,"z":-41.45,"y":21.07,"ts":1770749308,"ev":"Position"},{"x":180.11,"z":-41.62,"y":21.07,"ts":1770749318,"ev":"Position"},{"x":180.11,"z":-41.62,"y":21.07,"ts":1770749319,"ev":"Loot"},{"x":179.2,"z":-47.64,"y":21.02,"ts":1770749328,"ev":"Position"},{"x":180.27,"z":-41.86,"y":21.07,"ts":1770749333,"ev":"Position"},{"x":160.07,"z":-38.07,"y":21.02,"ts":1770749373,"ev":"Position"},{"x":146.15,"z":-43.94,"y":22.11,"ts":1770749378,"ev":"Position"},{"x":123.2,"z":-51.83,"y":25.65,"ts":1770749384,"ev":"Position"},{"x":99.35,"z":-67.51,"y":27.98,"ts":1770749389,"ev":"Position"},{"x":79.42,"z":-87.78,"y":27.33,"ts":1770749394,"ev":"Position"},{"x":64.64,"z":-106.81,"y":23.79,"ts":1770749399,"ev":"Position"},{"x":41.5,"z":-126.66,"y":23.8,"ts":1770749404,"ev":"Position"},{"x":17.18,"z":-133.11,"y":15.24,"ts":1770749409,"ev":"Position"},{"x":-2.37,"z":-121.71,"y":14.51,"ts":1770749414,"ev":"Position"},{"x":-23.93,"z":-108.04,"y":16.52,"ts":1770749419,"ev":"Position"},{"x":-24.9,"z":-88.96,"y":15.9,"ts":1770749424,"ev":"Position"},{"x":-24.9,"z":-88.96,"y":15.9,"ts":1770749432,"ev":"BotKill"},{"x":-24.66,"z":-85.19,"y":14.6,"ts":1770749434,"ev":"Position"},{"x":-19.64,"z":-81.12,"y":13.53,"ts":1770749439,"ev":"BotKill"},{"x":-19.79,"z":-81.31,"y":13.6,"ts":1770749439,"ev":"Position"},{"x":-26.85,"z":-81.57,"y":13.45,"ts":1770749444,"ev":"Position"},{"x":-27.81,"z":-78.97,"y":12.98,"ts":1770749449,"ev":"Position"},{"x":-29.47,"z":-79.1,"y":12.75,"ts":1770749452,"ev":"BotKill"},{"x":-26.66,"z":-80.73,"y":13.41,"ts":1770749454,"ev":"Position"},{"x":-26.38,"z":-80.69,"y":13.46,"ts":1770749455,"ev":"Loot"},{"x":-17.04,"z":-76.49,"y":11.82,"ts":1770749459,"ev":"Position"},{"x":-16.16,"z":-75.64,"y":11.49,"ts":1770749460,"ev":"Loot"},{"x":-9.11,"z":-66.03,"y":9.84,"ts":1770749463,"ev":"Loot"},{"x":-10.01,"z":-66.5,"y":9.93,"ts":1770749464,"ev":"Position"},{"x":-16.48,"z":-58.92,"y":10.21,"ts":1770749469,"ev":"Position"},{"x":-20.59,"z":-43.13,"y":9.13,"ts":1770749489,"ev":"Position"},{"x":-35.82,"z":-50.08,"y":9.13,"ts":1770749494,"ev":"Position"},{"x":-37.2,"z":-60.99,"y":9.11,"ts":1770749499,"ev":"Position"},{"x":-36.49,"z":-60.03,"y":12.35,"ts":1770749504,"ev":"Position"},{"x":-37.36,"z":-52.75,"y":13.88,"ts":1770749509,"ev":"Position"},{"x":-31.39,"z":-42.7,"y":15.44,"ts":1770749514,"ev":"Position"},{"x":-17.01,"z":-32.45,"y":15.46,"ts":1770749519,"ev":"Position"},{"x":-14.48,"z":-27.78,"y":8.81,"ts":1770749537,"ev":"BotKill"},{"x":-10.21,"z":-17.67,"y":8.77,"ts":1770749539,"ev":"Position"},{"x":-11.77,"z":-17.48,"y":8.85,"ts":1770749545,"ev":"BotKill"},{"x":-10.21,"z":-15.3,"y":8.76,"ts":1770749549,"ev":"Loot"},{"x":-9.94,"z":-15.53,"y":8.75,"ts":1770749549,"ev":"Position"},{"x":-9.94,"z":-15.53,"y":8.75,"ts":1770749562,"ev":"Loot"},{"x":-3.14,"z":-25.87,"y":8.63,"ts":1770749570,"ev":"Position"},{"x":15.88,"z":-33.11,"y":10.69,"ts":1770749575,"ev":"Position"},{"x":35.89,"z":-35.85,"y":15.44,"ts":1770749580,"ev":"Position"},{"x":52.26,"z":-40.84,"y":22.05,"ts":1770749585,"ev":"Position"},{"x":55.23,"z":-13.17,"y":26.76,"ts":1770749590,"ev":"Position"},{"x":84.04,"z":1.46,"y":27.57,"ts":1770749595,"ev":"Position"},{"x":100.27,"z":7.7,"y":31.15,"ts":1770749600,"ev":"Position"},{"x":116.28,"z":26.9,"y":32.3,"ts":1770749610,"ev":"Position"},{"x":121.17,"z":26.7,"y":31.96,"ts":1770749615,"ev":"Position"},{"x":141.96,"z":41.95,"y":31.18,"ts":1770749620,"ev":"Position"},{"x":156.65,"z":66.45,"y":36.36,"ts":1770749625,"ev":"Position"},{"x":166.14,"z":91.92,"y":37.03,"ts":1770749630,"ev":"Position"},{"x":175.62,"z":115.29,"y":35.18,"ts":1770749635,"ev":"Position"},{"x":184.18,"z":129.58,"y":32.27,"ts":1770749640,"ev":"Position"},{"x":183.21,"z":153.54,"y":31.67,"ts":1770749645,"ev":"Position"},{"x":179,"z":159.71,"y":31.4,"ts":1770749650,"ev":"Position"},{"x":180.81,"z":159.94,"y":31.47,"ts":1770749655,"ev":"Position"},{"x":179.85,"z":160.93,"y":31.43,"ts":1770749660,"ev":"Position"}]}]}