{"matchId":"1d360601-a6fe-424c-bc3b-85bd964115da","mapId":"GrandRift","date":"February_10","players":[{"userId":"f6829a66-7009-42bb-9d91-17add53fcc33","isBot":false,"events":[{"x":-106.72,"z":65.46,"y":21.72,"ts":1770695426,"ev":"Position"},{"x":-96.44,"z":79.05,"y":21.32,"ts":1770695441,"ev":"Position"},{"x":-103.27,"z":90.86,"y":20.34,"ts":1770695446,"ev":"Position"},{"x":-84.85,"z":114.51,"y":20.36,"ts":1770695452,"ev":"Position"},{"x":-97.63,"z":117.66,"y":20.76,"ts":1770695457,"ev":"Position"},{"x":-112.67,"z":131.24,"y":20.36,"ts":1770695462,"ev":"Position"},{"x":-101.95,"z":152.7,"y":20.39,"ts":1770695467,"ev":"Position"},{"x":-97.25,"z":156.86,"y":20.39,"ts":1770695472,"ev":"Position"},{"x":-82.22,"z":164.21,"y":20.39,"ts":1770695477,"ev":"Position"},{"x":-79.01,"z":153.81,"y":20.34,"ts":1770695482,"ev":"Position"},{"x":-62.34,"z":137.69,"y":20.46,"ts":1770695487,"ev":"Position"},{"x":-63.35,"z":113.96,"y":23.09,"ts":1770695492,"ev":"Position"},{"x":-64.68,"z":109.42,"y":22.61,"ts":1770695497,"ev":"Position"},{"x":-67.78,"z":110.01,"y":22.41,"ts":1770695502,"ev":"Position"},{"x":-76.64,"z":97.98,"y":20.49,"ts":1770695507,"ev":"Position"},{"x":-76.22,"z":94.93,"y":20.06,"ts":1770695512,"ev":"Position"},{"x":-89.85,"z":89.23,"y":20,"ts":1770695517,"ev":"Position"},{"x":-88.21,"z":90.25,"y":19.14,"ts":1770695522,"ev":"Position"},{"x":-88.34,"z":87.51,"y":20.25,"ts":1770695527,"ev":"Position"},{"x":-92.02,"z":89.31,"y":20.52,"ts":1770695532,"ev":"Position"},{"x":-90.68,"z":75.15,"y":21.55,"ts":1770695542,"ev":"BotKill"},{"x":-90.04,"z":74.79,"y":21.57,"ts":1770695542,"ev":"Position"},{"x":-91.14,"z":75.29,"y":21.52,"ts":1770695547,"ev":"Position"},{"x":-90.98,"z":74.75,"y":21.61,"ts":1770695547,"ev":"BotKill"},{"x":-90.98,"z":74.75,"y":21.61,"ts":1770695548,"ev":"BotKill"},{"x":-89.88,"z":72.83,"y":21.77,"ts":1770695567,"ev":"Position"},{"x":-90.42,"z":69.02,"y":21.87,"ts":1770695569,"ev":"Loot"},{"x":-90.58,"z":69.18,"y":21.87,"ts":1770695570,"ev":"Loot"},{"x":-89.9,"z":64.43,"y":21.84,"ts":1770695572,"ev":"Position"},{"x":-90.13,"z":58.03,"y":22,"ts":1770695574,"ev":"Loot"},{"x":-89.81,"z":58.34,"y":21.99,"ts":1770695575,"ev":"Loot"},{"x":-89.81,"z":58.34,"y":21.99,"ts":1770695576,"ev":"Loot"},{"x":-87.98,"z":55.01,"y":22.26,"ts":1770695577,"ev":"Position"},{"x":-87.75,"z":53.74,"y":22.32,"ts":1770695578,"ev":"Loot"},{"x":-87.75,"z":53.74,"y":22.32,"ts":1770695578,"ev":"Loot"},{"x":-93.68,"z":46.24,"y":22.68,"ts":1770695582,"ev":"Position"},{"x":-71.9,"z":42.54,"y":28.1,"ts":1770695587,"ev":"Position"},{"x":-64.31,"z":20.57,"y":32.62,"ts":1770695592,"ev":"Position"},{"x":-66.89,"z":18.69,"y":32.72,"ts":1770695597,"ev":"Position"},{"x":-68.28,"z":22.84,"y":32.81,"ts":1770695602,"ev":"Position"},{"x":-60.93,"z":30.01,"y":32.45,"ts":1770695617,"ev":"Position"},{"x":-62.33,"z":22.57,"y":32.37,"ts":1770695622,"ev":"Position"},{"x":-61.48,"z":23.2,"y":32.3,"ts":1770695629,"ev":"BotKill"},{"x":-65.04,"z":26.33,"y":32.48,"ts":1770695632,"ev":"Loot"},{"x":-64.18,"z":25.44,"y":32.47,"ts":1770695633,"ev":"Position"},{"x":-72.75,"z":16.49,"y":32.81,"ts":1770695638,"ev":"Position"},{"x":-76.2,"z":14.91,"y":32.85,"ts":1770695643,"ev":"Position"},{"x":-79.67,"z":9.34,"y":32.84,"ts":1770695648,"ev":"Position"},{"x":-79.67,"z":9.34,"y":32.84,"ts":1770695649,"ev":"Loot"},{"x":-92.66,"z":2.26,"y":32.96,"ts":1770695653,"ev":"Position"},{"x":-115.63,"z":-0.13,"y":35.26,"ts":1770695658,"ev":"Position"},{"x":-126.44,"z":-21.51,"y":38.46,"ts":1770695663,"ev":"Position"},{"x":-135.46,"z":-45.17,"y":38.34,"ts":1770695668,"ev":"Position"},{"x":-157.02,"z":-56.32,"y":38.72,"ts":1770695673,"ev":"Position"},{"x":-159.16,"z":-57.88,"y":38.66,"ts":1770695676,"ev":"Loot"},{"x":-156.95,"z":-48.49,"y":38.75,"ts":1770695683,"ev":"Position"},{"x":-166.54,"z":-52.76,"y":38.98,"ts":1770695688,"ev":"Position"},{"x":-174.22,"z":-52.53,"y":43.02,"ts":1770695693,"ev":"Position"},{"x":-162.78,"z":-54.82,"y":45.97,"ts":1770695698,"ev":"Position"},{"x":-161.1,"z":-56.36,"y":45.97,"ts":1770695702,"ev":"Loot"},{"x":-160.82,"z":-56.14,"y":45.97,"ts":1770695703,"ev":"Position"},{"x":-156.96,"z":-46.29,"y":38.83,"ts":1770695708,"ev":"Position"},{"x":-149.62,"z":-56.77,"y":38.48,"ts":1770695713,"ev":"Position"},{"x":-144.08,"z":-67.78,"y":37.79,"ts":1770695718,"ev":"Position"},{"x":-144.08,"z":-67.78,"y":37.79,"ts":1770695719,"ev":"Loot"},{"x":-144.08,"z":-67.78,"y":37.79,"ts":1770695719,"ev":"Loot"},{"x":-144.08,"z":-67.78,"y":37.79,"ts":1770695720,"ev":"Loot"},{"x":-148.38,"z":-69.28,"y":38,"ts":1770695723,"ev":"Position"},{"x":-148.3,"z":-58.58,"y":38.25,"ts":1770695733,"ev":"Position"},{"x":-148,"z":-63.18,"y":38.12,"ts":1770695738,"ev":"Position"},{"x":-148.16,"z":-65.47,"y":38.1,"ts":1770695743,"ev":"Position"},{"x":-143.98,"z":-87.6,"y":27.74,"ts":1770695753,"ev":"Position"},{"x":-139.07,"z":-107.2,"y":26.91,"ts":1770695758,"ev":"Position"},{"x":-118.94,"z":-126.52,"y":25.02,"ts":1770695763,"ev":"Position"},{"x":-98.26,"z":-142.78,"y":19.66,"ts":1770695768,"ev":"Position"},{"x":-74.46,"z":-156.38,"y":14.85,"ts":1770695773,"ev":"Position"},{"x":-53.15,"z":-155.28,"y":14.38,"ts":1770695778,"ev":"Position"},{"x":-33.02,"z":-135.08,"y":14.3,"ts":1770695783,"ev":"Position"},{"x":-43.8,"z":-119.88,"y":16.06,"ts":1770695788,"ev":"Position"},{"x":-44.35,"z":-120.19,"y":16.06,"ts":1770695793,"ev":"Position"},{"x":-36.42,"z":-121.12,"y":16.11,"ts":1770695803,"ev":"Position"},{"x":-21.62,"z":-95.9,"y":16.38,"ts":1770695809,"ev":"Position"},{"x":-10.36,"z":-66.29,"y":9.93,"ts":1770695814,"ev":"Position"},{"x":-10.01,"z":-59.33,"y":9.55,"ts":1770695818,"ev":"Loot"},{"x":-10.72,"z":-58.1,"y":9.21,"ts":1770695819,"ev":"Position"},{"x":-8.19,"z":-60.75,"y":9.67,"ts":1770695827,"ev":"Loot"},{"x":-7.61,"z":-61.17,"y":9.66,"ts":1770695828,"ev":"Loot"},{"x":-9.25,"z":-59.58,"y":9.6,"ts":1770695829,"ev":"Loot"},{"x":-9.59,"z":-59.49,"y":9.59,"ts":1770695829,"ev":"Position"},{"x":-8.53,"z":-57.16,"y":9.25,"ts":1770695829,"ev":"Loot"},{"x":-8.17,"z":-57.46,"y":9.38,"ts":1770695830,"ev":"Loot"},{"x":-8.29,"z":-54.72,"y":8.91,"ts":1770695833,"ev":"BotKill"},{"x":-8.44,"z":-54,"y":8.88,"ts":1770695834,"ev":"Position"},{"x":-3.59,"z":-40.79,"y":8.53,"ts":1770695839,"ev":"Position"},{"x":-10.55,"z":-43,"y":8.82,"ts":1770695844,"ev":"Position"},{"x":-8.95,"z":-46.15,"y":8.76,"ts":1770695848,"ev":"BotKill"},{"x":-9.13,"z":-49.18,"y":8.69,"ts":1770695849,"ev":"Position"},{"x":-9.21,"z":-47.45,"y":8.74,"ts":1770695851,"ev":"Loot"},{"x":-10.35,"z":-50.29,"y":8.79,"ts":1770695853,"ev":"Loot"},{"x":-10.35,"z":-50.29,"y":8.79,"ts":1770695853,"ev":"Loot"},{"x":-10.35,"z":-50.29,"y":8.79,"ts":1770695854,"ev":"Position"},{"x":-7.97,"z":-55,"y":8.96,"ts":1770695856,"ev":"Loot"},{"x":-9.15,"z":-56.85,"y":9.03,"ts":1770695859,"ev":"Position"},{"x":-19.83,"z":-64.33,"y":9.11,"ts":1770695864,"ev":"Position"},{"x":-39.04,"z":-52.63,"y":9.11,"ts":1770695869,"ev":"Position"},{"x":-39.01,"z":-53.33,"y":9.11,"ts":1770695881,"ev":"Loot"},{"x":-39.01,"z":-53.33,"y":9.11,"ts":1770695888,"ev":"Loot"},{"x":-22.81,"z":-37.78,"y":9.11,"ts":1770695899,"ev":"Position"},{"x":-31.96,"z":-31.91,"y":8.85,"ts":1770695909,"ev":"Position"},{"x":-31.82,"z":-43.61,"y":9.11,"ts":1770695914,"ev":"Position"},{"x":-31.82,"z":-43.61,"y":9.11,"ts":1770695915,"ev":"Loot"},{"x":-31.27,"z":-43.6,"y":9.11,"ts":1770695917,"ev":"Loot"},{"x":-33.58,"z":-38.94,"y":9.11,"ts":1770695919,"ev":"Position"},{"x":-30.28,"z":-53.21,"y":9.11,"ts":1770695924,"ev":"Position"},{"x":-27.62,"z":-51.84,"y":9.11,"ts":1770695929,"ev":"Position"},{"x":-20.08,"z":-52.56,"y":9.11,"ts":1770695939,"ev":"Position"},{"x":-19.53,"z":-52.72,"y":9.11,"ts":1770695944,"ev":"Position"},{"x":-23.05,"z":-55.71,"y":9.13,"ts":1770695949,"ev":"Position"},{"x":-26.37,"z":-46.69,"y":9.13,"ts":1770695954,"ev":"Position"},{"x":-30.5,"z":-56.31,"y":9.13,"ts":1770695969,"ev":"Position"},{"x":-29.88,"z":-66.78,"y":8.93,"ts":1770695974,"ev":"Position"},{"x":-22.49,"z":-90.66,"y":16.02,"ts":1770695979,"ev":"Position"},{"x":-43.74,"z":-107.4,"y":16.78,"ts":1770695984,"ev":"Position"},{"x":-72.43,"z":-111.19,"y":19.18,"ts":1770695990,"ev":"Position"},{"x":-87.02,"z":-102.44,"y":22.54,"ts":1770695995,"ev":"Position"},{"x":-73.66,"z":-86.39,"y":20.81,"ts":1770696000,"ev":"Position"},{"x":-71.07,"z":-59.34,"y":16.54,"ts":1770696005,"ev":"Position"},{"x":-72.59,"z":-34.43,"y":17.34,"ts":1770696010,"ev":"Position"},{"x":-77.6,"z":-10.08,"y":20.85,"ts":1770696015,"ev":"Position"},{"x":-86.02,"z":16.32,"y":23.92,"ts":1770696020,"ev":"Position"},{"x":-90.06,"z":26.65,"y":23.75,"ts":1770696025,"ev":"Position"},{"x":-90.17,"z":32.6,"y":23.54,"ts":1770696030,"ev":"Position"},{"x":-89.35,"z":58.26,"y":22.02,"ts":1770696035,"ev":"Position"},{"x":-87.71,"z":33.56,"y":23.55,"ts":1770696040,"ev":"Position"},{"x":-84.74,"z":11.14,"y":23.75,"ts":1770696045,"ev":"Position"},{"x":-76.83,"z":-11.3,"y":20.61,"ts":1770696050,"ev":"Position"},{"x":-72.44,"z":-23.89,"y":19.07,"ts":1770696055,"ev":"Position"},{"x":-70.69,"z":-45.26,"y":15.93,"ts":1770696065,"ev":"Position"},{"x":-68.1,"z":-59.77,"y":17.19,"ts":1770696070,"ev":"Position"},{"x":-69.89,"z":-84.88,"y":20.72,"ts":1770696075,"ev":"Position"},{"x":-94.04,"z":-99.17,"y":23.99,"ts":1770696080,"ev":"Position"},{"x":-115.19,"z":-105.91,"y":26.04,"ts":1770696085,"ev":"Position"},{"x":-133.79,"z":-113.44,"y":26.84,"ts":1770696090,"ev":"Position"}]}]}