{"matchId":"4eb7d365-3c0e-4c0d-a7f4-f8e869942b6d","mapId":"Lockdown","date":"February_10","players":[{"userId":"b3340cc5-c9fa-4108-b56d-0728bc978a22","isBot":false,"events":[{"x":-356.51,"z":-120.94,"y":53.89,"ts":1770759261,"ev":"Position"},{"x":-362.57,"z":-114.6,"y":53.42,"ts":1770759302,"ev":"Position"},{"x":-382.94,"z":-89.21,"y":51.74,"ts":1770759307,"ev":"Position"},{"x":-406.63,"z":-69.45,"y":50.7,"ts":1770759312,"ev":"Position"},{"x":-401.96,"z":-72.13,"y":50.81,"ts":1770759317,"ev":"Position"},{"x":-388.63,"z":-82.67,"y":51.36,"ts":1770759322,"ev":"Position"},{"x":-387.85,"z":-74.26,"y":51.12,"ts":1770759332,"ev":"Position"},{"x":-385.84,"z":-77.23,"y":51.26,"ts":1770759337,"ev":"Position"},{"x":-382.14,"z":-70.1,"y":50.48,"ts":1770759342,"ev":"Position"},{"x":-375.54,"z":-48.57,"y":43.64,"ts":1770759347,"ev":"Position"},{"x":-376.83,"z":-30.53,"y":41.48,"ts":1770759352,"ev":"Position"},{"x":-372.1,"z":-21.87,"y":41.55,"ts":1770759357,"ev":"Position"},{"x":-363.47,"z":-19.88,"y":41.5,"ts":1770759362,"ev":"Position"},{"x":-358.93,"z":-1.38,"y":40.75,"ts":1770759367,"ev":"Position"},{"x":-350.36,"z":29.13,"y":40.72,"ts":1770759372,"ev":"Position"},{"x":-348.53,"z":41.84,"y":41.74,"ts":1770759377,"ev":"Position"},{"x":-345.25,"z":47.34,"y":42.32,"ts":1770759382,"ev":"Position"},{"x":-345.14,"z":53.94,"y":42.99,"ts":1770759387,"ev":"Position"},{"x":-337.54,"z":56.76,"y":43.31,"ts":1770759392,"ev":"Position"},{"x":-340.68,"z":44.24,"y":41.48,"ts":1770759402,"ev":"Position"},{"x":-337.6,"z":44.7,"y":41.11,"ts":1770759407,"ev":"Position"},{"x":-340.89,"z":38.9,"y":40.52,"ts":1770759417,"ev":"Position"},{"x":-354.06,"z":9.05,"y":39.89,"ts":1770759422,"ev":"Position"},{"x":-358.07,"z":-18.61,"y":40.96,"ts":1770759427,"ev":"Position"},{"x":-328.43,"z":-4.61,"y":39.97,"ts":1770759432,"ev":"Position"},{"x":-321.78,"z":6.77,"y":40.47,"ts":1770759437,"ev":"Position"},{"x":-296.67,"z":11.5,"y":41.42,"ts":1770759442,"ev":"Position"},{"x":-289.44,"z":18.86,"y":41.6,"ts":1770759447,"ev":"Position"},{"x":-285.65,"z":14.81,"y":42.22,"ts":1770759452,"ev":"Position"},{"x":-273.08,"z":9.8,"y":42.58,"ts":1770759457,"ev":"Position"},{"x":-273.5,"z":13.3,"y":42.25,"ts":1770759462,"ev":"Position"},{"x":-268.89,"z":21.81,"y":41.36,"ts":1770759467,"ev":"Position"},{"x":-269.74,"z":40.85,"y":40.6,"ts":1770759473,"ev":"Position"},{"x":-280.42,"z":49.63,"y":40.54,"ts":1770759478,"ev":"Position"},{"x":-283.37,"z":54.71,"y":40.48,"ts":1770759483,"ev":"Position"},{"x":-285.18,"z":54.55,"y":40.61,"ts":1770759493,"ev":"Position"},{"x":-289.38,"z":55.05,"y":40.69,"ts":1770759498,"ev":"Position"},{"x":-289.81,"z":54.88,"y":40.69,"ts":1770759503,"ev":"Position"},{"x":-294.58,"z":56.21,"y":40.69,"ts":1770759513,"ev":"Position"},{"x":-293.15,"z":60.2,"y":40.69,"ts":1770759518,"ev":"Position"},{"x":-289.87,"z":60.97,"y":40.69,"ts":1770759528,"ev":"Position"},{"x":-291.27,"z":59.62,"y":40.69,"ts":1770759538,"ev":"Position"},{"x":-292.91,"z":54.68,"y":40.69,"ts":1770759543,"ev":"Position"},{"x":-297.06,"z":57.55,"y":40.69,"ts":1770759548,"ev":"Position"},{"x":-304.43,"z":53.8,"y":40.69,"ts":1770759563,"ev":"Position"},{"x":-296.07,"z":59.51,"y":40.69,"ts":1770759578,"ev":"Position"},{"x":-293.39,"z":60.91,"y":40.69,"ts":1770759583,"ev":"Position"},{"x":-293.24,"z":56.32,"y":40.69,"ts":1770759588,"ev":"Position"},{"x":-288.43,"z":55.81,"y":40.69,"ts":1770759593,"ev":"Position"},{"x":-298.26,"z":57.99,"y":40.69,"ts":1770759598,"ev":"Position"},{"x":-298.05,"z":61.07,"y":40.69,"ts":1770759603,"ev":"Position"},{"x":-296.72,"z":58.28,"y":40.69,"ts":1770759623,"ev":"Position"},{"x":-295.24,"z":62,"y":40.69,"ts":1770759628,"ev":"Position"},{"x":-285.94,"z":84.1,"y":40.63,"ts":1770759633,"ev":"Position"},{"x":-284.62,"z":90.19,"y":40.63,"ts":1770759638,"ev":"Position"},{"x":-295.68,"z":90.92,"y":40.63,"ts":1770759643,"ev":"Position"},{"x":-287.82,"z":90.89,"y":40.63,"ts":1770759649,"ev":"Position"},{"x":-285.89,"z":84.71,"y":40.63,"ts":1770759654,"ev":"Position"},{"x":-304.35,"z":80.23,"y":40.65,"ts":1770759664,"ev":"Position"},{"x":-307.35,"z":71.62,"y":40.65,"ts":1770759669,"ev":"Position"},{"x":-308.19,"z":68.7,"y":40.65,"ts":1770759674,"ev":"Position"},{"x":-308.08,"z":68.68,"y":40.65,"ts":1770759705,"ev":"Loot"},{"x":-306.76,"z":78.81,"y":40.65,"ts":1770759724,"ev":"Position"},{"x":-304.4,"z":83.73,"y":40.65,"ts":1770759729,"ev":"Position"},{"x":-303.95,"z":84.11,"y":40.65,"ts":1770759734,"ev":"Loot"},{"x":-306.11,"z":84.06,"y":40.65,"ts":1770759739,"ev":"Position"},{"x":-306.29,"z":77.72,"y":40.65,"ts":1770759744,"ev":"Position"},{"x":-307.94,"z":71.77,"y":40.65,"ts":1770759754,"ev":"Position"},{"x":-302.17,"z":70.89,"y":40.63,"ts":1770759759,"ev":"Position"},{"x":-292.89,"z":66.5,"y":40.64,"ts":1770759764,"ev":"Position"},{"x":-293.55,"z":54.93,"y":40.69,"ts":1770759769,"ev":"Position"},{"x":-294.72,"z":61.2,"y":40.69,"ts":1770759774,"ev":"Position"},{"x":-299.4,"z":83.68,"y":40.63,"ts":1770759779,"ev":"Position"},{"x":-304.39,"z":86.92,"y":40.51,"ts":1770759784,"ev":"Position"},{"x":-307.78,"z":94.78,"y":44.27,"ts":1770759789,"ev":"Position"},{"x":-304.3,"z":91.5,"y":46.49,"ts":1770759794,"ev":"Position"},{"x":-307.51,"z":93.84,"y":44.27,"ts":1770759809,"ev":"Position"},{"x":-309.45,"z":86.07,"y":40.38,"ts":1770759814,"ev":"Position"},{"x":-308.28,"z":93.69,"y":40.5,"ts":1770759819,"ev":"Position"},{"x":-319.36,"z":99.05,"y":40.24,"ts":1770759825,"ev":"Position"},{"x":-313.53,"z":98.95,"y":40.24,"ts":1770759830,"ev":"Position"},{"x":-297.64,"z":96.92,"y":40.65,"ts":1770759835,"ev":"Position"},{"x":-289.44,"z":93.37,"y":40.65,"ts":1770759840,"ev":"Position"},{"x":-296.29,"z":95.5,"y":40.65,"ts":1770759845,"ev":"Position"},{"x":-302.03,"z":94.84,"y":40.65,"ts":1770759850,"ev":"Position"},{"x":-303.06,"z":96.91,"y":40.65,"ts":1770759855,"ev":"Position"},{"x":-301.45,"z":88.43,"y":40.65,"ts":1770759860,"ev":"Position"},{"x":-308.02,"z":62.05,"y":40.68,"ts":1770759865,"ev":"Position"},{"x":-291.16,"z":48.34,"y":40.64,"ts":1770759870,"ev":"Position"},{"x":-283.97,"z":50.32,"y":40.55,"ts":1770759875,"ev":"Position"},{"x":-281.36,"z":55.77,"y":40.47,"ts":1770759890,"ev":"Position"},{"x":-281.52,"z":60.87,"y":40.52,"ts":1770759895,"ev":"Position"},{"x":-285.71,"z":63.19,"y":40.65,"ts":1770759900,"ev":"Position"},{"x":-283.65,"z":65.98,"y":40.65,"ts":1770759915,"ev":"Position"},{"x":-266.47,"z":64.83,"y":40.43,"ts":1770759925,"ev":"Position"},{"x":-258.51,"z":54.93,"y":40.5,"ts":1770759930,"ev":"Position"},{"x":-273.94,"z":34.94,"y":40.71,"ts":1770759935,"ev":"Position"},{"x":-278.44,"z":27.7,"y":41.18,"ts":1770759940,"ev":"Position"},{"x":-279.23,"z":15.26,"y":42.2,"ts":1770759945,"ev":"Position"},{"x":-272.66,"z":38.25,"y":40.64,"ts":1770759955,"ev":"Position"},{"x":-265.71,"z":61.22,"y":40.47,"ts":1770759960,"ev":"Position"},{"x":-270.85,"z":82.54,"y":40.62,"ts":1770759965,"ev":"Position"},{"x":-271.21,"z":90.04,"y":40.69,"ts":1770759970,"ev":"Position"},{"x":-272.41,"z":87.96,"y":40.6,"ts":1770759975,"ev":"Position"},{"x":-267.8,"z":92,"y":40.51,"ts":1770759990,"ev":"Position"},{"x":-242.21,"z":95.64,"y":51.93,"ts":1770760000,"ev":"Position"},{"x":-217.98,"z":88.77,"y":53.33,"ts":1770760006,"ev":"Position"},{"x":-242.9,"z":95.67,"y":52.36,"ts":1770760016,"ev":"Position"},{"x":-262.79,"z":100.76,"y":41.1,"ts":1770760021,"ev":"Position"},{"x":-287.48,"z":103.96,"y":40.65,"ts":1770760026,"ev":"Position"},{"x":-310.01,"z":114.42,"y":40.65,"ts":1770760031,"ev":"Position"},{"x":-301.8,"z":118.42,"y":40.66,"ts":1770760036,"ev":"Position"},{"x":-307.84,"z":122.12,"y":40.77,"ts":1770760041,"ev":"Position"},{"x":-307.85,"z":128.32,"y":40.77,"ts":1770760046,"ev":"Position"},{"x":-307.88,"z":130.99,"y":40.77,"ts":1770760051,"ev":"Position"},{"x":-307.88,"z":130.99,"y":40.77,"ts":1770760061,"ev":"KilledByStorm"}]}]}